bequests/__init__.py
bequests/bequests.py
bequests-0.1.0.dist-info/METADATA
bequests-0.1.0.dist-info/WHEEL
bequests-0.1.0.dist-info/RECORD
