Metadata-Version: 2.4
Name: bequests
Version: 0.1.0
Summary: Stealth HTTP Engine for Python
Author: PainDe0Mie
Requires-Dist: curl-cffi
